{"chunk_definitions":[{"chunk_id":"c6z5ijogdsnc2","chunk_label":"unnamed-chunk-2","document_id":"88A352A2","expansion_state":0,"options":{"cache":false,"echo":false,"engine":"r","label":"unnamed-chunk-6"},"row":80,"row_count":1,"visible":true},{"chunk_id":"cy0kuz298ejs8","chunk_label":"unnamed-chunk-3","document_id":"88A352A2","expansion_state":0,"options":{"engine":"r","label":"unnamed-chunk-7"},"row":84,"row_count":1,"visible":true},{"chunk_id":"chx0fy7somxmc","chunk_label":"unnamed-chunk-5","document_id":"88A352A2","expansion_state":0,"options":{"engine":"r","label":"unnamed-chunk-5"},"row":103,"row_count":1,"visible":true},{"chunk_id":"cug32u390mf1y","chunk_label":"unnamed-chunk-10","document_id":"88A352A2","expansion_state":0,"options":{"engine":"r","label":"unnamed-chunk-3","message":false},"row":158,"row_count":1,"visible":true},{"chunk_id":"cjka5ggtmh0m0","chunk_label":"unnamed-chunk-12","document_id":"88A352A2","expansion_state":0,"options":{"engine":"r","label":"unnamed-chunk-4"},"row":178,"row_count":1,"visible":true},{"chunk_id":"cy33ot3os24kj","chunk_label":"unnamed-chunk-15","document_id":"88A352A2","expansion_state":0,"options":{"engine":"r","label":"unnamed-chunk-2"},"row":197,"row_count":1,"visible":true},{"chunk_id":"co5i9f15pexp8","chunk_label":"unnamed-chunk-17","document_id":"88A352A2","expansion_state":0,"options":{"engine":"r","label":"unnamed-chunk-1"},"row":211,"row_count":1,"visible":true}],"doc_write_time":1579738660}